Predatamaker/Predatamaker.py
Predatamaker/__init__.py
Predatamaker-0.0.5.dist-info/LICENCE
Predatamaker-0.0.5.dist-info/METADATA
Predatamaker-0.0.5.dist-info/WHEEL
Predatamaker-0.0.5.dist-info/top_level.txt
Predatamaker-0.0.5.dist-info/RECORD
