Metadata-Version: 2.1
Name: Predatamaker
Version: 0.0.5
Summary: Ajuda na utilização de dados
Author-email: gabrielqs543543@gmail.com
License: MIT License
Keywords: Predatamaker
License-File: LICENCE
Requires-Dist: pandas
